lazytype.py
lazytype-0.2.1.dist-info/LICENSE
lazytype-0.2.1.dist-info/WHEEL
lazytype-0.2.1.dist-info/METADATA
lazytype-0.2.1.dist-info/RECORD
