Metadata-Version: 2.1
Name: lazytype
Version: 0.2.1
Summary: Wrappers for typing & pydantic models; module loading deferred till __init__.
Home-page: https://github.com/stefco/lazytype
License: UNKNOWN
Author: Stefan Trklja Countryman
Author-email: stefan.countryman@gmail.com
Requires-Python: >=3
Classifier: License :: OSI Approved :: GNU General Public License v3 or later (GPLv3+)
Classifier: Development Status :: 4 - Beta
Classifier: Programming Language :: Python :: 3 :: Only
Classifier: Topic :: Software Development :: Libraries :: Python Modules
Classifier: Intended Audience :: Developers
Classifier: Intended Audience :: Science/Research
Requires-Dist: pydantic ; extra == "pydantic"
Provides-Extra: pydantic
